{
    "page": 319,
    "result": [
        {
            "transcription": "愁樹没𠳨竹寧冲殺",
            "points": [
                [
                    356,
                    383
                ],
                [
                    393,
                    382
                ],
                [
                    401,
                    704
                ],
                [
                    364,
                    705
                ]
            ],
            "difficult": false
        },
        {
            "transcription": "󰋇番油𣺽牡汀",
            "points": [
                [
                    345,
                    57
                ],
                [
                    384,
                    55
                ],
                [
                    393,
                    272
                ],
                [
                    354,
                    274
                ]
            ],
            "difficult": false
        },
        {
            "transcription": "經駟𧘇决浽碎󰑼𣌉",
            "points": [
                [
                    301,
                    386
                ],
                [
                    337,
                    385
                ],
                [
                    352,
                    698
                ],
                [
                    316,
                    700
                ]
            ],
            "difficult": false
        },
        {
            "transcription": "刼𨓡吒𪱆庒󰠐",
            "points": [
                [
                    293,
                    63
                ],
                [
                    332,
                    62
                ],
                [
                    340,
                    274
                ],
                [
                    300,
                    276
                ]
            ],
            "difficult": false
        },
        {
            "transcription": "牢𠸼冲料買浽𭛣茹",
            "points": [
                [
                    252,
                    385
                ],
                [
                    288,
                    384
                ],
                [
                    298,
                    704
                ],
                [
                    263,
                    706
                ]
            ],
            "difficult": false
        },
        {
            "transcription": "𧘇經𥐆拱󰡏撑",
            "points": [
                [
                    241,
                    62
                ],
                [
                    279,
                    60
                ],
                [
                    288,
                    278
                ],
                [
                    250,
                    280
                ]
            ],
            "difficult": false
        },
        {
            "transcription": "󰝸𦖑旨拱沛𦖑買苓",
            "points": [
                [
                    199,
                    389
                ],
                [
                    236,
                    388
                ],
                [
                    247,
                    707
                ],
                [
                    210,
                    709
                ]
            ],
            "difficult": false
        },
        {
            "transcription": "壙緣箕弹𢴑乙牢",
            "points": [
                [
                    189,
                    28
                ],
                [
                    227,
                    27
                ],
                [
                    235,
                    288
                ],
                [
                    197,
                    289
                ]
            ],
            "difficult": false
        },
        {
            "transcription": "𠊛諸夾𨦩𠊛情𡳃牢",
            "points": [
                [
                    144,
                    391
                ],
                [
                    181,
                    390
                ],
                [
                    193,
                    721
                ],
                [
                    155,
                    722
                ]
            ],
            "difficult": false
        },
        {
            "transcription": "刼迻秦眷弹迢",
            "points": [
                [
                    136,
                    68
                ],
                [
                    174,
                    68
                ],
                [
                    176,
                    284
                ],
                [
                    138,
                    285
                ]
            ],
            "difficult": false
        },
        {
            "transcription": "𢜠昆𥰊夾𢜠妯森同",
            "points": [
                [
                    84,
                    393
                ],
                [
                    126,
                    391
                ],
                [
                    140,
                    715
                ],
                [
                    98,
                    717
                ]
            ],
            "difficult": false
        },
        {
            "transcription": "䜹𨖅淑𠬠好庭",
            "points": [
                [
                    76,
                    67
                ],
                [
                    118,
                    66
                ],
                [
                    125,
                    286
                ],
                [
                    83,
                    287
                ]
            ],
            "difficult": false
        },
        {
            "transcription": "哙娘妯買計𥞁事緣",
            "points": [
                [
                    30,
                    388
                ],
                [
                    74,
                    387
                ],
                [
                    86,
                    715
                ],
                [
                    42,
                    717
                ]
            ],
            "difficult": false
        },
        {
            "transcription": "决北𠹾𬌓𨓡世",
            "points": [
                [
                    25,
                    72
                ],
                [
                    63,
                    71
                ],
                [
                    70,
                    285
                ],
                [
                    32,
                    286
                ]
            ],
            "difficult": false
        }
    ]
}