{
    "page": 425,
    "result": [
        {
            "transcription": "段棦㐌𤼸庒案産泥",
            "points": [
                [
                    359,
                    367
                ],
                [
                    398,
                    366
                ],
                [
                    402,
                    644
                ],
                [
                    364,
                    644
                ]
            ],
            "difficult": false
        },
        {
            "transcription": "恩𩄲濁牢𠁑灵",
            "points": [
                [
                    357,
                    52
                ],
                [
                    395,
                    51
                ],
                [
                    401,
                    266
                ],
                [
                    363,
                    267
                ]
            ],
            "difficult": false
        },
        {
            "transcription": "段𠆳謝笠𫥨𧗱",
            "points": [
                [
                    311,
                    50
                ],
                [
                    349,
                    50
                ],
                [
                    352,
                    255
                ],
                [
                    313,
                    256
                ]
            ],
            "difficult": false
        },
        {
            "transcription": "㗂󰑼移楼橋𣘃率𨂘",
            "points": [
                [
                    309,
                    364
                ],
                [
                    347,
                    363
                ],
                [
                    353,
                    645
                ],
                [
                    315,
                    645
                ]
            ],
            "difficult": false
        },
        {
            "transcription": "󰒂𣘈𬋟丿󰜋孝",
            "points": [
                [
                    263,
                    52
                ],
                [
                    301,
                    52
                ],
                [
                    301,
                    250
                ],
                [
                    263,
                    250
                ]
            ],
            "difficult": false
        },
        {
            "transcription": "𠻵𦝄𫮇𩙌蜂𡢐坤墮",
            "points": [
                [
                    259,
                    366
                ],
                [
                    296,
                    365
                ],
                [
                    298,
                    652
                ],
                [
                    261,
                    652
                ]
            ],
            "difficult": false
        },
        {
            "transcription": "𠰘󰑼𩄲逴𠬠𦋦欣",
            "points": [
                [
                    211,
                    7
                ],
                [
                    248,
                    7
                ],
                [
                    248,
                    246
                ],
                [
                    211,
                    246
                ]
            ],
            "difficult": false
        },
        {
            "transcription": "𨢇權𣿌衝𠃣悶𫭧釆",
            "points": [
                [
                    209,
                    368
                ],
                [
                    246,
                    369
                ],
                [
                    244,
                    651
                ],
                [
                    207,
                    651
                ]
            ],
            "difficult": false
        },
        {
            "transcription": "扽絲𡶀𢮿𥘷𠫾",
            "points": [
                [
                    157,
                    51
                ],
                [
                    192,
                    51
                ],
                [
                    192,
                    255
                ],
                [
                    157,
                    255
                ]
            ],
            "difficult": false
        },
        {
            "transcription": "󰝡神蜆𨤔渧𧗱塘𫅷",
            "points": [
                [
                    157,
                    367
                ],
                [
                    191,
                    367
                ],
                [
                    191,
                    654
                ],
                [
                    157,
                    654
                ]
            ],
            "difficult": false
        },
        {
            "transcription": "㝹𦖑󰒂庶𠴗汀",
            "points": [
                [
                    104,
                    51
                ],
                [
                    143,
                    51
                ],
                [
                    141,
                    257
                ],
                [
                    101,
                    256
                ]
            ],
            "difficult": false
        },
        {
            "transcription": "尋种昆襖求命瑰𢗼",
            "points": [
                [
                    102,
                    364
                ],
                [
                    141,
                    364
                ],
                [
                    141,
                    660
                ],
                [
                    102,
                    660
                ]
            ],
            "difficult": false
        },
        {
            "transcription": "𠀧𤤰脱別根由",
            "points": [
                [
                    50,
                    57
                ],
                [
                    88,
                    57
                ],
                [
                    88,
                    252
                ],
                [
                    50,
                    252
                ]
            ],
            "difficult": false
        },
        {
            "transcription": "沛𠫾添恪矯󰋇銀𮥷",
            "points": [
                [
                    50,
                    364
                ],
                [
                    87,
                    364
                ],
                [
                    87,
                    651
                ],
                [
                    50,
                    651
                ]
            ],
            "difficult": false
        }
    ]
}