{
    "page": 251,
    "result": [
        {
            "transcription": "如林城奇矯筭𠫾滁",
            "points": [
                [
                    369,
                    370
                ],
                [
                    407,
                    369
                ],
                [
                    415,
                    691
                ],
                [
                    377,
                    691
                ]
            ],
            "difficult": false
        },
        {
            "transcription": "執渚顕夾函逐",
            "points": [
                [
                    362,
                    46
                ],
                [
                    400,
                    45
                ],
                [
                    405,
                    261
                ],
                [
                    366,
                    262
                ]
            ],
            "difficult": false
        },
        {
            "transcription": "哭如敬𩯀達除異端",
            "points": [
                [
                    313,
                    370
                ],
                [
                    354,
                    369
                ],
                [
                    360,
                    688
                ],
                [
                    319,
                    688
                ]
            ],
            "difficult": false
        },
        {
            "transcription": "矯群綏几呌魂",
            "points": [
                [
                    311,
                    49
                ],
                [
                    350,
                    48
                ],
                [
                    355,
                    263
                ],
                [
                    317,
                    264
                ]
            ],
            "difficult": false
        },
        {
            "transcription": "𩯀彩空𦝄歲褚󰥎牟",
            "points": [
                [
                    266,
                    370
                ],
                [
                    302,
                    369
                ],
                [
                    304,
                    694
                ],
                [
                    268,
                    694
                ]
            ],
            "difficult": false
        },
        {
            "transcription": "拱群𡗋几諸信",
            "points": [
                [
                    263,
                    48
                ],
                [
                    301,
                    48
                ],
                [
                    305,
                    263
                ],
                [
                    267,
                    264
                ]
            ],
            "difficult": false
        },
        {
            "transcription": "路𥙩道娶爫頭紅孥",
            "points": [
                [
                    213,
                    371
                ],
                [
                    250,
                    370
                ],
                [
                    254,
                    695
                ],
                [
                    217,
                    695
                ]
            ],
            "difficult": false
        },
        {
            "transcription": "𠰘𥐆𤁕盘泊式饒",
            "points": [
                [
                    207,
                    14
                ],
                [
                    248,
                    13
                ],
                [
                    252,
                    267
                ],
                [
                    211,
                    268
                ]
            ],
            "difficult": false
        },
        {
            "transcription": "沛𧗱公論底朱精詳",
            "points": [
                [
                    152,
                    369
                ],
                [
                    193,
                    368
                ],
                [
                    201,
                    697
                ],
                [
                    160,
                    698
                ]
            ],
            "difficult": false
        },
        {
            "transcription": "朱牢丞奇北㗍",
            "points": [
                [
                    151,
                    51
                ],
                [
                    193,
                    51
                ],
                [
                    195,
                    261
                ],
                [
                    153,
                    261
                ]
            ],
            "difficult": false
        },
        {
            "transcription": "俸󰠳喧㗂𨔍荄",
            "points": [
                [
                    97,
                    49
                ],
                [
                    139,
                    49
                ],
                [
                    142,
                    266
                ],
                [
                    100,
                    267
                ]
            ],
            "difficult": false
        },
        {
            "transcription": "啫鴻紅𠦳哙𠹾劍咹",
            "points": [
                [
                    96,
                    366
                ],
                [
                    137,
                    365
                ],
                [
                    144,
                    695
                ],
                [
                    102,
                    695
                ]
            ],
            "difficult": false
        },
        {
            "transcription": "𠊛𠀧計奴如神主迻",
            "points": [
                [
                    44,
                    368
                ],
                [
                    83,
                    367
                ],
                [
                    89,
                    695
                ],
                [
                    51,
                    695
                ]
            ],
            "difficult": false
        },
        {
            "transcription": "窻爫萡水終身",
            "points": [
                [
                    40,
                    56
                ],
                [
                    78,
                    54
                ],
                [
                    84,
                    266
                ],
                [
                    46,
                    267
                ]
            ],
            "difficult": false
        }
    ]
}