{
    "page": 63,
    "result": [
        {
            "transcription": "四十四",
            "points": [
                [
                    422,
                    478
                ],
                [
                    451,
                    478
                ],
                [
                    451,
                    549
                ],
                [
                    422,
                    549
                ]
            ],
            "difficult": false
        },
        {
            "transcription": "芇㐌針𠰺𥙩昆渚𦒹𢆥旦欺戈代時户壮客紇終於茹蜍没長",
            "points": [
                [
                    361,
                    117
                ],
                [
                    381,
                    117
                ],
                [
                    392,
                    631
                ],
                [
                    372,
                    632
                ]
            ],
            "difficult": false
        },
        {
            "transcription": "𤾓𥛉共仕迻堯仍空麻𠊚茹空沛秩之吏户仕嗔󰜋禮墓咍󰑼",
            "points": [
                [
                    332,
                    119
                ],
                [
                    353,
                    119
                ],
                [
                    364,
                    630
                ],
                [
                    343,
                    631
                ]
            ],
            "difficult": false
        },
        {
            "transcription": "汲禮鑑蜍隨户輸閉隔𠨪",
            "points": [
                [
                    306,
                    120
                ],
                [
                    326,
                    120
                ],
                [
                    331,
                    339
                ],
                [
                    312,
                    339
                ]
            ],
            "difficult": false
        },
        {
            "transcription": "調次穆",
            "points": [
                [
                    270,
                    337
                ],
                [
                    302,
                    336
                ],
                [
                    306,
                    448
                ],
                [
                    274,
                    449
                ]
            ],
            "difficult": false
        },
        {
            "transcription": "術事學儒學國",
            "points": [
                [
                    245,
                    315
                ],
                [
                    266,
                    314
                ],
                [
                    270,
                    465
                ],
                [
                    249,
                    466
                ]
            ],
            "difficult": false
        },
        {
            "transcription": "名",
            "points": [
                [
                    222,
                    91
                ],
                [
                    295,
                    91
                ],
                [
                    295,
                    105
                ],
                [
                    222,
                    105
                ]
            ],
            "difficult": false
        },
        {
            "transcription": "次一座理㐌傳庒仍󰑼沛立塲竝廊吏沛料朱𥙩昆翠儒翠斜",
            "points": [
                [
                    214,
                    120
                ],
                [
                    234,
                    120
                ],
                [
                    244,
                    631
                ],
                [
                    224,
                    632
                ]
            ],
            "difficult": false
        },
        {
            "transcription": "分代貝柴固道矯學貝柴外道分時料命默編分時𠫾吏濫",
            "points": [
                [
                    187,
                    123
                ],
                [
                    204,
                    123
                ],
                [
                    214,
                    630
                ],
                [
                    197,
                    631
                ]
            ],
            "difficult": false
        },
        {
            "transcription": "貝几外道時常學仍事罪共𦖑呐𧗱塘詐𧗱事󰊄學神事",
            "points": [
                [
                    159,
                    121
                ],
                [
                    178,
                    121
                ],
                [
                    188,
                    631
                ],
                [
                    168,
                    632
                ]
            ],
            "difficult": false
        },
        {
            "transcription": "供翁妑翁偈化牌寅寅𡳒命寧朝𧗱仍事𧘇共傕容𨱽塞橘坦",
            "points": [
                [
                    131,
                    120
                ],
                [
                    151,
                    120
                ],
                [
                    160,
                    631
                ],
                [
                    140,
                    632
                ]
            ],
            "difficult": false
        },
        {
            "transcription": "以",
            "points": [
                [
                    105,
                    95
                ],
                [
                    111,
                    95
                ],
                [
                    111,
                    100
                ],
                [
                    105,
                    100
                ]
            ],
            "difficult": false
        },
        {
            "transcription": "㙴𠯇各役醒詐聰兎排達朱特𠼦𡎢𠊚些虚𠫾廊沙地鸞",
            "points": [
                [
                    102,
                    120
                ],
                [
                    123,
                    120
                ],
                [
                    131,
                    591
                ],
                [
                    110,
                    591
                ]
            ],
            "difficult": false
        }
    ]
}