{
    "page": 380,
    "result": [
        {
            "transcription": "敬劍淑假固期罪碎仕合𩈘貝淑逃天堂家囂𠸦從主丞瓊代空紀",
            "points": [
                [
                    345,
                    113
                ],
                [
                    372,
                    114
                ],
                [
                    346,
                    646
                ],
                [
                    319,
                    645
                ]
            ],
            "difficult": false
        },
        {
            "transcription": "經偷望衮那超𥛉恩翁整衣鄕超初㐌𠀧神也間共各李属𧗱怒朱𢧚㐌特",
            "points": [
                [
                    309,
                    92
                ],
                [
                    336,
                    93
                ],
                [
                    310,
                    656
                ],
                [
                    283,
                    655
                ]
            ],
            "difficult": false
        },
        {
            "transcription": "婵爲共璜號姑嘉吳登曷役爫於達公嚴澤骨翁聖永那趨求朱嚴碎",
            "points": [
                [
                    275,
                    109
                ],
                [
                    298,
                    110
                ],
                [
                    273,
                    641
                ],
                [
                    250,
                    640
                ]
            ],
            "difficult": false
        },
        {
            "transcription": "當召𥙩仍𭓇主基𥘷吹尊㐌芽𥛉恩初主丞初㐌𪮙翁整永那超丘",
            "points": [
                [
                    237,
                    107
                ],
                [
                    261,
                    109
                ],
                [
                    235,
                    643
                ],
                [
                    211,
                    642
                ]
            ],
            "difficult": false
        },
        {
            "transcription": "𣳔中會聖朱迄󰆙主蚕刘湥每將天下辰嚴碎吀徇主傷旦嚴碎哭乱",
            "points": [
                [
                    201,
                    106
                ],
                [
                    226,
                    108
                ],
                [
                    198,
                    642
                ],
                [
                    172,
                    641
                ]
            ],
            "difficult": false
        },
        {
            "transcription": "浽澍𥊘召恩淑求朱罪碎當欺打賊声灵於世間尼萃叔斫歇朱當",
            "points": [
                [
                    165,
                    104
                ],
                [
                    189,
                    106
                ],
                [
                    159,
                    636
                ],
                [
                    135,
                    635
                ]
            ],
            "difficult": false
        },
        {
            "transcription": "尊福𠴗𨤔於達丞爲局主支状秦移次尊𡎝主派潙沚端",
            "points": [
                [
                    128,
                    98
                ],
                [
                    154,
                    100
                ],
                [
                    126,
                    590
                ],
                [
                    100,
                    589
                ]
            ],
            "difficult": false
        }
    ]
}