{
    "page": 407,
    "result": [
        {
            "transcription": "些㐌萱定自尼𧗱楼仕濫碎佐德主𡗶仕濫昆丐德媄係󰑼昆",
            "points": [
                [
                    405,
                    106
                ],
                [
                    425,
                    105
                ],
                [
                    428,
                    603
                ],
                [
                    408,
                    603
                ]
            ],
            "difficult": false
        },
        {
            "transcription": "丐群敢補帽吒媄女時𠽐罸眾昆於世間尼傷喂眾昆󰑼物之",
            "points": [
                [
                    377,
                    106
                ],
                [
                    397,
                    106
                ],
                [
                    400,
                    604
                ],
                [
                    380,
                    604
                ]
            ],
            "difficult": false
        },
        {
            "transcription": "常仕𥙩飭塊麻樑把斫魔鬼仕濫体帶廊㑏𡳒凭傍𥛉德媄眾",
            "points": [
                [
                    351,
                    107
                ],
                [
                    371,
                    107
                ],
                [
                    374,
                    603
                ],
                [
                    354,
                    603
                ]
            ],
            "difficult": false
        },
        {
            "transcription": "昆嘆𤼸懇魂𠯇堯𬂙𢬣德媄嗔德婵扶護朱几要𭔰嘆𡨹𡳒眾",
            "points": [
                [
                    325,
                    108
                ],
                [
                    344,
                    107
                ],
                [
                    348,
                    604
                ],
                [
                    329,
                    604
                ]
            ],
            "difficult": false
        },
        {
            "transcription": "芒",
            "points": [
                [
                    279,
                    54
                ],
                [
                    326,
                    47
                ],
                [
                    329,
                    69
                ],
                [
                    282,
                    75
                ]
            ],
            "difficult": false
        },
        {
            "transcription": "昆瀝罪朱旦𧷺代腹𨃴德主𠳒𠀧聰創名媄主𡗶顯眾昆實敬",
            "points": [
                [
                    299,
                    107
                ],
                [
                    319,
                    107
                ],
                [
                    321,
                    602
                ],
                [
                    301,
                    602
                ]
            ],
            "difficult": false
        },
        {
            "transcription": "地於代足渚之吏特敬勉代代無窮",
            "points": [
                [
                    271,
                    108
                ],
                [
                    291,
                    107
                ],
                [
                    293,
                    395
                ],
                [
                    273,
                    395
                ]
            ],
            "difficult": false
        },
        {
            "transcription": "亞綿",
            "points": [
                [
                    275,
                    414
                ],
                [
                    293,
                    414
                ],
                [
                    293,
                    458
                ],
                [
                    275,
                    458
                ]
            ],
            "difficult": false
        },
        {
            "transcription": "經求嘆共慄理德妃俘命朱特仁德瀝涖",
            "points": [
                [
                    246,
                    231
                ],
                [
                    266,
                    231
                ],
                [
                    268,
                    564
                ],
                [
                    248,
                    564
                ]
            ],
            "difficult": false
        },
        {
            "transcription": "眾碎𥛉恩慄醒德妑瑀移亞嘆德妑𥙩事󰞺准如𦀊廊𫃚朱碎",
            "points": [
                [
                    218,
                    107
                ],
                [
                    238,
                    107
                ],
                [
                    239,
                    601
                ],
                [
                    219,
                    601
                ]
            ],
            "difficult": false
        },
        {
            "transcription": "嘆破事顯動濕𢗼𬂙命碎嘆𫴋仁德瀝油朱碎朱特當𡃹𨆢慄",
            "points": [
                [
                    191,
                    107
                ],
                [
                    210,
                    107
                ],
                [
                    213,
                    601
                ],
                [
                    194,
                    601
                ]
            ],
            "difficult": false
        },
        {
            "transcription": "理德妑共弹慄理德如扶護朱碎特飭環把各斫几畵靈柳碎",
            "points": [
                [
                    163,
                    107
                ],
                [
                    184,
                    107
                ],
                [
                    186,
                    601
                ],
                [
                    165,
                    601
                ]
            ],
            "difficult": false
        },
        {
            "transcription": "理教經願",
            "points": [
                [
                    116,
                    165
                ],
                [
                    143,
                    165
                ],
                [
                    143,
                    266
                ],
                [
                    116,
                    266
                ]
            ],
            "difficult": false
        },
        {
            "transcription": "二百一",
            "points": [
                [
                    118,
                    480
                ],
                [
                    142,
                    480
                ],
                [
                    142,
                    540
                ],
                [
                    118,
                    540
                ]
            ],
            "difficult": false
        }
    ]
}