{
    "page": 458,
    "result": [
        {
            "transcription": "柴吏黜󰀋没吝女時些沛吟浪德主支秋傷名苔伵如昆季時",
            "points": [
                [
                    356,
                    93
                ],
                [
                    376,
                    93
                ],
                [
                    379,
                    598
                ],
                [
                    359,
                    598
                ]
            ],
            "difficult": false
        },
        {
            "transcription": "𠊚於吏世間𦊚𨑮𣈜女廊安慰𨀈𡭧名苔伵時些沛願浪碎",
            "points": [
                [
                    329,
                    113
                ],
                [
                    349,
                    113
                ],
                [
                    351,
                    597
                ],
                [
                    331,
                    597
                ]
            ],
            "difficult": false
        },
        {
            "transcription": "𥛉德主支秋碎嘆主碎恒汝旦碎渚神昆閑曳突尼謚之",
            "points": [
                [
                    304,
                    115
                ],
                [
                    321,
                    115
                ],
                [
                    324,
                    580
                ],
                [
                    307,
                    580
                ]
            ],
            "difficult": false
        },
        {
            "transcription": "柴濫卧畧󰘚些𧘇髀欺德主支秋啫各苔伵廊遁𡗶",
            "points": [
                [
                    274,
                    93
                ],
                [
                    294,
                    93
                ],
                [
                    297,
                    515
                ],
                [
                    278,
                    515
                ]
            ],
            "difficult": false
        },
        {
            "transcription": "柴郎𬂙𠽋翁理由安醒史義押欺德主理洳現𫴋段各墨宗𠻀",
            "points": [
                [
                    247,
                    93
                ],
                [
                    267,
                    93
                ],
                [
                    270,
                    599
                ],
                [
                    250,
                    599
                ]
            ],
            "difficult": false
        },
        {
            "transcription": "𥙩𠫾講道朱奇𠯇天下川塘󰊄奉德主𡗶時些沛推師事傷",
            "points": [
                [
                    221,
                    116
                ],
                [
                    238,
                    116
                ],
                [
                    241,
                    597
                ],
                [
                    224,
                    597
                ]
            ],
            "difficult": false
        },
        {
            "transcription": "庫名噐宗徒𠹾哩各柴𣈜徽扒斫如丕朱特識𠴗些適廊些",
            "points": [
                [
                    195,
                    116
                ],
                [
                    213,
                    116
                ],
                [
                    215,
                    597
                ],
                [
                    197,
                    597
                ]
            ],
            "difficult": false
        },
        {
            "transcription": "強𣈜強亘恶庒悌德主𡗶罸補𫴋火獄如核󰛎園㐌數靜",
            "points": [
                [
                    167,
                    116
                ],
                [
                    186,
                    116
                ],
                [
                    188,
                    597
                ],
                [
                    169,
                    597
                ]
            ],
            "difficult": false
        },
        {
            "transcription": "麻庄生卿花第之時年制共焠𠫾󱀄渚於謨淹茹他渚迷事",
            "points": [
                [
                    140,
                    116
                ],
                [
                    158,
                    116
                ],
                [
                    160,
                    596
                ],
                [
                    142,
                    596
                ]
            ],
            "difficult": false
        },
        {
            "transcription": "世間庄絲渚貪役分琵收𣈘收𣈜過理濫之唉底汲𠃣𣈜賒",
            "points": [
                [
                    111,
                    116
                ],
                [
                    131,
                    116
                ],
                [
                    132,
                    597
                ],
                [
                    112,
                    597
                ]
            ],
            "difficult": false
        }
    ]
}