{
    "Sach-Nom-Cong-Giao-1995-001": {
        "qn": [
            [
                2,
                2
            ],
            [
                4,
                112
            ]
        ],
        "nom": [
            [
                217,
                113
            ]
        ]
    },
    "Sach-Nom-Cong-Giao-1995-002": {
        "qn": [     // left = 0.069 right = 0.03 top = 0.1053 bottom = 0.0263
            [
                5,    // trang 5 cắt 0.54 left, cắt top = 0.13
                17
            ]
        ],
        "nom": [ // left = 0.043 right = 0.046 top = 0.078 bottom = 0.0521
            [
                62, // trang 62 cắt 0.5 bên phải , cắt 0.09 top
                18  // trang 18 cắt 0.5 bên trái , cắt 0.09 top
            ]
        ]
    },
    "Sach-Nom-Cong-Giao-1995-004": {
        "qn": [
            [
                12,
                54
            ],
            [
                146,
                161
            ]
        ],
        "nom": [
            [
                95,
                55
            ],
            [
                173,
                163
            ]
        ]
    },
    "Sach-Nom-Cong-Giao-1995-005": {
        "qn": [
            [
                6,
                170
            ]
        ],
        "nom": [
            [
                341,
                171
            ]
        ]
    },
    "Sach-Nom-Cong-Giao-1995-008": {
        "qn": [
            [
                8,
                93
            ]
        ],
        "nom": [
            [
                8,
                93
            ]
        ]
    },
    "Sach-Nom-Cong-Giao-1995-012": {
        "qn": [
            [
                9,
                25
            ],
            [
                55,
                65
            ],
            [
                82,
                101
            ]
        ],
        "nom": [
            [
                54,
                26
            ],
            [
                82,
                66
            ],
            [
                134,
                102
            ]
        ]
    },
    "Sach-Nom-Cong-Giao-1995-049": {
        "qn": [
            11,
            156
        ],
        "nom": [
            298,
            157
        ]
    }
}