{
    "page": 58,
    "result": [
        {
            "transcription": "姉澄時吒媄拱害年底獸意奴悶𧗱𣅶芇咍󰑼悶𠫾忤洳茹𠊚",
            "points": [
                [
                    335,
                    102
                ],
                [
                    359,
                    102
                ],
                [
                    357,
                    621
                ],
                [
                    334,
                    621
                ]
            ],
            "difficult": false
        },
        {
            "transcription": "些矯沛貴命𧗱徽",
            "points": [
                [
                    310,
                    101
                ],
                [
                    331,
                    101
                ],
                [
                    328,
                    259
                ],
                [
                    307,
                    258
                ]
            ],
            "difficult": false
        },
        {
            "transcription": "火𦊚𧗱事孕𡢻妸𫯳朱昆丐吒媄渚料命蹺意盈蹺仍理世間",
            "points": [
                [
                    279,
                    102
                ],
                [
                    302,
                    102
                ],
                [
                    302,
                    620
                ],
                [
                    279,
                    620
                ]
            ],
            "difficult": false
        },
        {
            "transcription": "貪興事郎重錢𧵑過理爲烝昆丐𥙩𠊚𠃣䀡雙踏苔頭道時欣",
            "points": [
                [
                    254,
                    105
                ],
                [
                    271,
                    105
                ],
                [
                    271,
                    619
                ],
                [
                    254,
                    619
                ]
            ],
            "difficult": false
        },
        {
            "transcription": "押𥙩𠊚覇固仍麻枯道庫性吏渚倍麻𢗼顯過欺准邊群性𥙩",
            "points": [
                [
                    224,
                    104
                ],
                [
                    244,
                    104
                ],
                [
                    244,
                    620
                ],
                [
                    224,
                    620
                ]
            ],
            "difficult": false
        },
        {
            "transcription": "矯庄包數生不平庫𢚸沛徐𠃣牌旦𨑮𦒹𨔿罷歳買年料廊崔",
            "points": [
                [
                    198,
                    106
                ],
                [
                    215,
                    106
                ],
                [
                    215,
                    619
                ],
                [
                    198,
                    619
                ]
            ],
            "difficult": false
        },
        {
            "transcription": "次𠄼如㐌傳囷事結伴𢆥畧欺算料時吒媄沛󰏙堆邊固順𥙩",
            "points": [
                [
                    169,
                    104
                ],
                [
                    189,
                    104
                ],
                [
                    189,
                    619
                ],
                [
                    169,
                    619
                ]
            ],
            "difficult": false
        },
        {
            "transcription": "饒實庄裊眾奴空順時空特押爲事泛固罪共生牌𡗉事興朱",
            "points": [
                [
                    142,
                    106
                ],
                [
                    159,
                    106
                ],
                [
                    159,
                    618
                ],
                [
                    142,
                    618
                ]
            ],
            "difficult": false
        },
        {
            "transcription": "吒媄𠯇朱堆𨔈㜮𫯳計庄翠𡲤吏畧欺認朔沛迻𠄩溋旦呈柴",
            "points": [
                [
                    114,
                    106
                ],
                [
                    133,
                    106
                ],
                [
                    133,
                    620
                ],
                [
                    114,
                    620
                ]
            ],
            "difficult": false
        },
        {
            "transcription": "奇底𠊚查𠳨眾奴固順𠯇固默垠阻之庄耒計自𣈜認𢆥時排",
            "points": [
                [
                    83,
                    103
                ],
                [
                    106,
                    103
                ],
                [
                    106,
                    621
                ],
                [
                    83,
                    621
                ]
            ],
            "difficult": false
        }
    ]
}