{
    "page": 534,
    "result": [
        {
            "transcription": "欺時眾碎讀經吝紇𫀅册學行𣅶時經脱𠯇仍勾涓於",
            "points": [
                [
                    409,
                    130
                ],
                [
                    433,
                    130
                ],
                [
                    426,
                    648
                ],
                [
                    401,
                    647
                ]
            ],
            "difficult": false
        },
        {
            "transcription": "茹圭如初民㩜姚沛答於渃巴悲崙時嘱仍經濁喝於茹圭序",
            "points": [
                [
                    379,
                    130
                ],
                [
                    400,
                    130
                ],
                [
                    392,
                    648
                ],
                [
                    371,
                    647
                ]
            ],
            "difficult": false
        },
        {
            "transcription": "麻觧煩",
            "points": [
                [
                    337,
                    124
                ],
                [
                    372,
                    124
                ],
                [
                    372,
                    199
                ],
                [
                    337,
                    199
                ]
            ],
            "difficult": false
        },
        {
            "transcription": "欺翁妻爲絶泥郎邊尼時富浪沙諸鎌解坦士",
            "points": [
                [
                    342,
                    261
                ],
                [
                    363,
                    261
                ],
                [
                    356,
                    647
                ],
                [
                    336,
                    646
                ]
            ],
            "difficult": false
        },
        {
            "transcription": "捥渃衣支蘇朱年艚諸𠫾𤎕麻郎邊尼特沛𠫾觥方南𥹰深困",
            "points": [
                [
                    307,
                    128
                ],
                [
                    330,
                    128
                ],
                [
                    322,
                    646
                ],
                [
                    298,
                    645
                ]
            ],
            "difficult": false
        },
        {
            "transcription": "艚𠫾没𢆥固艚𠫾老󰑼𣎃艚翁妻爲𥪝泥𢵼特固𠀧𣎃麻催時",
            "points": [
                [
                    271,
                    128
                ],
                [
                    295,
                    128
                ],
                [
                    286,
                    646
                ],
                [
                    263,
                    645
                ]
            ],
            "difficult": false
        },
        {
            "transcription": "旦鋪買󰑼󰠮遊属𧗱摧紅毛該治各柴奇𧗱會󰕖道朱各民外",
            "points": [
                [
                    235,
                    131
                ],
                [
                    257,
                    131
                ],
                [
                    250,
                    645
                ],
                [
                    228,
                    644
                ]
            ],
            "difficult": false
        },
        {
            "transcription": "時講道於塊衣𠯇奇沔鄰近共固茹𡨹役於帝拱如於香港不",
            "points": [
                [
                    199,
                    127
                ],
                [
                    223,
                    127
                ],
                [
                    215,
                    646
                ],
                [
                    190,
                    645
                ]
            ],
            "difficult": false
        },
        {
            "transcription": "翁妻烏龜泥堵步於鋪買朱特尋艚𨔾命旦香港爲艚略𨔾𠊚",
            "points": [
                [
                    165,
                    126
                ],
                [
                    187,
                    126
                ],
                [
                    177,
                    645
                ],
                [
                    156,
                    644
                ]
            ],
            "difficult": false
        },
        {
            "transcription": "固旦帝麻崔空於賖欣女",
            "points": [
                [
                    127,
                    126
                ],
                [
                    151,
                    126
                ],
                [
                    148,
                    343
                ],
                [
                    124,
                    343
                ]
            ],
            "difficult": false
        },
        {
            "transcription": "當欺翁妻烏蔽泥擬󰋇𣈜於茹",
            "points": [
                [
                    125,
                    387
                ],
                [
                    146,
                    388
                ],
                [
                    140,
                    644
                ],
                [
                    120,
                    643
                ]
            ],
            "difficult": false
        },
        {
            "transcription": "故𡨹役在鋪買時固𠄼老注茹柴地分双安德柴厚𠳚郎學場",
            "points": [
                [
                    92,
                    125
                ],
                [
                    115,
                    125
                ],
                [
                    106,
                    646
                ],
                [
                    82,
                    645
                ]
            ],
            "difficult": false
        }
    ]
}